ex1_cross_clock_domain_single_bit/src/ex1_puls_sync.v
`timescale 1ns/1ps

module pulse_sync (
    input wire clk_fast, clk_slow,
    input wire in_fast,
    output wire out_slow
);

// pulse from fast domain -> toggle
reg toggle = 0;
always @(posedge clk_fast) begin
    if (in_fast)
        toggle <= !toggle;
    else 
        toggle <= toggle; 
end

// dual trigger synchronizer
reg delay0, delay1, delay2;
always @(posedge clk_slow) begin
    {delay2, delay1, delay0} <= {delay1, delay0, toggle}; 
end

// toggle -> pulse in slow domain 
assign out_slow = delay1 ^ delay2;

initial begin
    $dumpfile("pulse_sync.vcd");
    $dumpvars(0, pulse_sync);
end
endmodule

ex1_cross_clock_domain_single_bit/sim/test_puls_sync/pulse_sync.vcd
$date
	Mon Mar  1 21:52:23 2021
$end

$version
	Synopsys VCS version L-2016.06_Full64
$end

$timescale
	1ps
$end

$comment Csum: 1 7572f9424a930519 $end


$scope module pulse_sync $end
$var wire 1 ! clk_fast $end
$var wire 1 " clk_slow $end
$var wire 1 # in_fast $end
$var wire 1 $ out_slow $end
$var reg 1 % toggle $end
$var reg 1 & delay0 $end
$var reg 1 ' delay1 $end
$var reg 1 ( delay2 $end
$upscope $end

$enddefinitions $end

#0
$dumpvars
0&
x'
x(
0%
x$
1!
1"
0#
$end
#1000
0!
#2000
1!
#2500
0"
#3000
0!
#4000
1!
#5000
1"
0!
0'
#6000
1!
1#
#7000
0!
#7500
0"
#8000
1!
0#
1%
#9000
0!
#10000
1"
1!
0(
0$
1&
#11000
0!
#12000
1!
#12500
0"
#13000
0!
#14000
1!
#15000
1"
0!
1'
1$
#16000
1!
#17000
0!
#17500
0"
#18000
1!
#19000
0!
#20000
1"
1!
1(
0$
#21000
0!
#22000
1!
1#
#22500
0"
#23000
0!
#24000
1!
0#
0%
#25000
1"
0!
0&
#26000
1!
#27000
0!
#27500
0"
#28000
1!
#29000
0!
#30000
1"
1!
0'
1$
#31000
0!
#32000
1!
#32500
0"
#33000
0!
#34000
1!
#35000
1"
0!
0(
0$
#36000
1!
#37000
0!
#37500
0"
#38000
1!
#39000
0!
#40000
1"
1!
#41000
0!
#42000
1!
#42500
0"
#43000
0!
#44000
1!
1#
#45000
1"
0!
#46000
1!
0#
1%
#47000
0!
#47500
0"
#48000
1!
#49000
0!
#50000
1"
1!
1#
1&
#51000
0!
#52000
1!
0#
0%
#52500
0"
#53000
0!
#54000
1!
#55000
1"
0!
1'
1$
0&
#56000
1!
#57000
0!
#57500
0"
#58000
1!
#59000
0!
#60000
1"
1!
1(
0'
#61000
0!
#62000
1!
#62500
0"
#63000
0!
#64000
1!
#65000
1"
0!
0(
0$
